{"title":"Telos / 利马计划·档案库","uid":"27b1bcaf55a8a37b585c67c3f6b50470","slug":"公告发布/置顶头图模块","date":"2022-01-11T15:37:43.069Z","updated":"2022-01-13T15:47:10.206Z","comments":true,"path":"api/articles/公告发布/置顶头图模块.json","keywords":null,"cover":null,"content":"<p><strong>借助三金羊Sheep的广大法力，利马计划档案库向各位执棋者开放了！</strong></p>\n<p><strong>在这个网站，各位执棋者可以查看人物设定、世界设定以及大陆杂设——一切你不了解的东西都可以在这里查询。</strong></p>\n<p><strong>资料目前正在陆续上传到本站，如果没有找到自己想要的，可以向 LD小迪 索要相关资料~</strong></p>\n<blockquote><span class=\"custom-blockquote-svg\"><svg width=\"24\" height=\"24\" viewBox=\"0 0 24 24\" fill=\"\" xmlns=\"http://www.w3.org/2000/svg\" data-reactroot=\"\">\n<path fill=\"\" d=\"M22 12C22 6.5 17.5 2 12 2C6.5 2 2 6.5 2 12C2 17.5 6.5 22 12 22C13.8 22 15.5 21.5 17 20.6L22 22L20.7 17C21.5 15.5 22 13.8 22 12Z\" undefined=\"1\"></path>\n<path fill=\"\" d=\"M15.97 11.5H16.04C17.12 11.5 18 12.38 18 13.47V13.53C18 14.62 17.12 15.5 16.03 15.5H15.96C14.88 15.5 14 14.62 14 13.53V13.46C14 12.38 14.88 11.5 15.97 11.5Z\" undefined=\"1\"></path>\n<path fill=\"\" d=\"M7.97 11.5H8.04C9.12 11.5 10 12.38 10 13.47V13.53C10 14.62 9.12 15.5 8.03 15.5H7.97C6.88 15.5 6 14.62 6 13.53V13.46C6 12.38 6.88 11.5 7.97 11.5Z\" undefined=\"1\"></path>\n<path stroke-linejoin=\"round\" stroke-linecap=\"round\" stroke-miterlimit=\"10\" stroke-width=\"2\" stroke=\"\" d=\"M17 8.5C15.23 8.97 14.07 10.84 14.01 13.27C14 13.33 14 13.4 14 13.47V13.5\"></path>\n<path stroke-linejoin=\"round\" stroke-linecap=\"round\" stroke-miterlimit=\"10\" stroke-width=\"2\" stroke=\"\" d=\"M9 8.5C7.23 8.97 6.07 10.84 6.01 13.27C6 13.33 6 13.4 6 13.47V13.5\"></path>\n<path stroke-linejoin=\"round\" stroke-linecap=\"round\" stroke-miterlimit=\"10\" stroke-width=\"2\" stroke=\"\" d=\"M15.97 11.5H16.04C17.12 11.5 18 12.38 18 13.47V13.53C18 14.62 17.12 15.5 16.03 15.5H15.96C14.88 15.5 14 14.62 14 13.53V13.46C14 12.38 14.88 11.5 15.97 11.5Z\"></path>\n<path stroke-linejoin=\"round\" stroke-linecap=\"round\" stroke-miterlimit=\"10\" stroke-width=\"2\" stroke=\"\" d=\"M7.97 11.5H8.04C9.12 11.5 10 12.38 10 13.47V13.53C10 14.62 9.12 15.5 8.03 15.5H7.97C6.88 15.5 6 14.62 6 13.53V13.46C6 12.38 6.88 11.5 7.97 11.5Z\"></path>\n</svg>\n</span><p>好了，就这么多了，开始你的浏览吧！</p>\n<p>————LD小迪</p></blockquote>\n","feature":true,"text":"借助三金羊Sheep的广大法力，利马计划档案库向各位执棋者开放了！ 在这个网站，各位执棋者可以查看人物设定、世界设定以及大陆杂设——一切你不了解的东西都可以在这里查询。 资料目前正在陆续上传到本站，如果没有找到自己想要的，可以向 LD小迪 索要相关资料~ 好了，就这么多了，开始你...","link":"","photos":[],"count_time":{"symbolsCount":164,"symbolsTime":"1 mins."},"categories":[{"name":"公告发布","slug":"公告发布","count":1,"path":"api/categories/公告发布.json"}],"tags":[],"toc":"","author":{"name":"LDxiaodi","slug":"blog-author","avatar":"/images/ldxiaodi.jpg","link":"/","description":"这里是利马计划档案室。<br/>存储着设定和档案的最高知识库。","socials":{"github":"","twitter":"","stackoverflow":"","wechat":"","qq":"","weibo":"","zhihu":"","csdn":"","juejin":"","customs":{}}},"mapped":true,"prev_post":{"title":"王","uid":"9f21b2fbf7ce2615f5dba2d6ef30ad3d","slug":"人物足迹/王","date":"2022-01-12T14:31:04.155Z","updated":"2022-01-12T14:34:23.255Z","comments":true,"path":"api/articles/人物足迹/王.json","keywords":null,"cover":null,"text":"“哈…哈…” 一位银发兽耳的少年在大火吞没的森林里穿梭，他看起来像是在逃跑。 “不能…辜负了族人的期待…我要跑…哈，我要跑…” “在那里，抓住这个逃跑的灾星！” 一群拿着锐利武器收操火把的狂热群众发现了他，人们从四面八方赶向这边。 “迪，你要逃离这里...我已经不行了。我会利用最...","link":"","photos":[],"count_time":{"symbolsCount":"1.1k","symbolsTime":"1 mins."},"categories":[{"name":"人物足迹","slug":"人物足迹","count":3,"path":"api/categories/人物足迹.json"}],"tags":[{"name":"γ","slug":"γ","count":2,"path":"api/tags/γ.json"}],"author":{"name":"LDxiaodi","slug":"blog-author","avatar":"/images/ldxiaodi.jpg","link":"/","description":"这里是利马计划档案室。<br/>存储着设定和档案的最高知识库。","socials":{"github":"","twitter":"","stackoverflow":"","wechat":"","qq":"","weibo":"","zhihu":"","csdn":"","juejin":"","customs":{}}},"feature":true},"next_post":{"title":"英普瑞斯","uid":"db45af6e957464cf17dc7f8fc624f8b6","slug":"人物档案/英普瑞斯","date":"2022-01-11T16:11:11.799Z","updated":"2022-01-12T14:22:48.756Z","comments":true,"path":"api/articles/人物档案/英普瑞斯.json","keywords":null,"cover":null,"text":"基础档案 利马综合评估 【代号】英普瑞斯 【性别】男 【生日】12.12 【种族】未知，由外观特征推测其为阿兰雪尔 【身高】178cm 【综合症寄宿情况】参照利马检测报告，确认为非宿主。 综合体检测试 Juzi全大陆覆盖系统评估 【物理强度】标准 【战场机动】卓越 【生理耐受】标...","link":"","photos":[],"count_time":{"symbolsCount":"1.2k","symbolsTime":"1 mins."},"categories":[{"name":"人物档案","slug":"人物档案","count":16,"path":"api/categories/人物档案.json"}],"tags":[],"author":{"name":"LDxiaodi","slug":"blog-author","avatar":"/images/ldxiaodi.jpg","link":"/","description":"这里是利马计划档案室。<br/>存储着设定和档案的最高知识库。","socials":{"github":"","twitter":"","stackoverflow":"","wechat":"","qq":"","weibo":"","zhihu":"","csdn":"","juejin":"","customs":{}}}}}